sc_employee_synchronizer/__init__.py
sc_employee_synchronizer/main.py
sc_employee_synchronizer/api/__init__.py
sc_employee_synchronizer/api/request_api.py
sc_employee_synchronizer/db/__init__.py
sc_employee_synchronizer/db/common_db_module.py
sc_employee_synchronizer/db/common_sql.py
sc_employee_synchronizer/db/json2db.py
sc_employee_synchronizer/exception/__init__.py
sc_employee_synchronizer/exception/exceptions.py
sc_employee_synchronizer/sync/__init__.py
sc_employee_synchronizer/sync/employee_sync.py
sc_employee_synchronizer/tests/__init__.py
sc_employee_synchronizer/tests/sample_config/production.yml
sc_employee_synchronizer/utils/__init__.py
sc_employee_synchronizer/utils/conversion_utils.py
sc_employee_synchronizer-0.0.4.dist-info/licenses/LICENSE
tests/__init__.py
tests/sync/__init__.py
tests/sync/test_employee_sync.py
sc_employee_synchronizer-0.0.4.dist-info/METADATA
sc_employee_synchronizer-0.0.4.dist-info/WHEEL
sc_employee_synchronizer-0.0.4.dist-info/entry_points.txt
sc_employee_synchronizer-0.0.4.dist-info/top_level.txt
sc_employee_synchronizer-0.0.4.dist-info/RECORD
