Metadata-Version: 2.4
Name: sc-employee-synchronizer
Version: 0.0.4
Summary: Employee synchronizer
Home-page: https://github.com/Scott-Lau/sc-employee-synchronizer
Author: Scott Lau
Author-email: exceedego@126.com
License: MIT
Keywords: python employee synchronizer
Platform: POSIX
Classifier: Programming Language :: Python :: 3
Classifier: Programming Language :: Python :: 3.6
Classifier: Programming Language :: Python :: 3.7
Classifier: Programming Language :: Python :: 3.8
Classifier: Programming Language :: Python :: 3.9
Classifier: License :: OSI Approved :: MIT License
Classifier: Operating System :: OS Independent
Classifier: Topic :: Software Development
Classifier: Topic :: Utilities
Requires-Python: >=3.6
License-File: LICENSE
Requires-Dist: sc-utilities>=0.0.7
Requires-Dist: sc-config>=0.0.14
Requires-Dist: requests>=2.26.0
Requires-Dist: urllib3>=1.26.6
Requires-Dist: sc-mysqlhelper>=0.1.4
Dynamic: author
Dynamic: author-email
Dynamic: classifier
Dynamic: description
Dynamic: home-page
Dynamic: keywords
Dynamic: license
Dynamic: license-file
Dynamic: platform
Dynamic: requires-dist
Dynamic: requires-python
Dynamic: summary
